autodft/__init__.py
autodft/config/__init__.py
autodft/config/config.py
autodft/config/default_parameters.yaml
autodft/helpers/__init__.py
autodft/helpers/crest_job.py
autodft/helpers/gaussian_inputfile.py
autodft/helpers/gaussian_manager.py
autodft/helpers/user_input.py
autodft/utils/__init__.py
autodft/utils/autodft_utils.py
autodft/utils/files.py
autodft/utils/gaussian_output.py
autodft-1.0.4.data/data/LICENSE.txt
autodft-1.0.4.data/data/README.md
autodft-1.0.4.data/scripts/autodft_flow.py
autodft-1.0.4.data/scripts/autodft_flow_xyz.py
autodft-1.0.4.data/scripts/compile_results.py
autodft-1.0.4.data/scripts/gstatus.py
autodft-1.0.4.data/scripts/run_autodft.py
autodft-1.0.4.data/scripts/run_autodft_xyz.py
autodft-1.0.4.dist-info/LICENSE.txt
autodft-1.0.4.dist-info/METADATA
autodft-1.0.4.dist-info/WHEEL
autodft-1.0.4.dist-info/top_level.txt
autodft-1.0.4.dist-info/RECORD
