Metadata-Version: 2.1
Name: autodft
Version: 1.0.4
Summary: Automated conformer searching and DFT calculations
Home-page: https://github.com/shenvilab/autodft
Author: Shenvi Lab
Author-email: sting@scripps.edu
License: GPL-v3
Requires-Python: >=3.10
License-File: LICENSE.txt
Requires-Dist: rdkit >=2022.03.1
Requires-Dist: pandas
Requires-Dist: goodvibes >=3.2
Requires-Dist: cclib
Requires-Dist: pyyaml >=6.0
